{
  "batch_id": "session_20250713_005207_3e682b41_round_02",
  "timestamp": "2025-07-13T00:52:10.219379",
  "total_execution_time": 1289.0822887420654,
  "total_cost": 4.8,
  "success_rate": 1.0,
  "average_quality": 0.40131982404158323,
  "session_count": 8,
  "session_results": [
    {
      "session_id": "session_20250713_005208_1f3d92",
      "query": "せつなは歌系の活動者です。主な活動として歌を用いたMusicVideoの投稿を考えていますが、それだけだと投稿頻度に難があるとも考えています。\n今後人気や知名度を獲得していくにあたって、既存の歌系インフルエンサー、動画投稿者、VTuberなどがどのようなコンテンツを制作しているか人気なのかを調査し、自身がどのような方針で活動していくかの判断材料を集めて、分析してください の優位性の応用可能性 の将来性",
      "status": "success",
      "execution_time": 702.2813298057242,
      "quality_score": 0.4079806272822466,
      "cost": 0.6,
      "themes_found": [
        "リスク要因",
        "実用化"
      ],
      "error": null
    },
    {
      "session_id": "session_20250713_005208_069561",
      "query": "せつなは歌系の活動者です。主な活動として歌を用いたMusicVideoの投稿を考えていますが、それだけだと投稿頻度に難があるとも考えています。\n今後人気や知名度を獲得していくにあたって、既存の歌系インフルエンサー、動画投稿者、VTuberなどがどのようなコンテンツを制作しているか人気なのかを調査し、自身がどのような方針で活動していくかの判断材料を集めて、分析してください の定義と概要の研究動向 の詳細分析",
      "status": "success",
      "execution_time": 782.6268576075549,
      "quality_score": 0.47459635010793355,
      "cost": 0.6,
      "themes_found": [
        "市場動向",
        "ユーザビリティ"
      ],
      "error": null
    },
    {
      "session_id": "session_20250713_005208_1f3d92",
      "query": "せつなは歌系の活動者です。主な活動として歌を用いたMusicVideoの投稿を考えていますが、それだけだと投稿頻度に難があるとも考えています。\n今後人気や知名度を獲得していくにあたって、既存の歌系インフルエンサー、動画投稿者、VTuberなどがどのようなコンテンツを制作しているか人気なのかを調査し、自身がどのような方針で活動していくかの判断材料を集めて、分析してください の応用分野の技術分析 の課題と解決策",
      "status": "success",
      "execution_time": 861.8959602254683,
      "quality_score": 0.3549242387724755,
      "cost": 0.6,
      "themes_found": [
        "実用化"
      ],
      "error": null
    },
    {
      "session_id": "session_20250713_005208_1f3d92",
      "query": "せつなは歌系の活動者です。主な活動として歌を用いたMusicVideoの投稿を考えていますが、それだけだと投稿頻度に難があるとも考えています。\n今後人気や知名度を獲得していくにあたって、既存の歌系インフルエンサー、動画投稿者、VTuberなどがどのようなコンテンツを制作しているか人気なのかを調査し、自身がどのような方針で活動していくかの判断材料を集めて、分析してください について教えての技術分析",
      "status": "success",
      "execution_time": 885.3868019554627,
      "quality_score": 0.42325527648084044,
      "cost": 0.6,
      "themes_found": [
        "課題解決",
        "競合分析"
      ],
      "error": null
    },
    {
      "session_id": "session_20250713_005208_1f3d92",
      "query": "せつなは歌系の活動者です。主な活動として歌を用いたMusicVideoの投稿を考えていますが、それだけだと投稿頻度に難があるとも考えています。\n今後人気や知名度を獲得していくにあたって、既存の歌系インフルエンサー、動画投稿者、VTuberなどがどのようなコンテンツを制作しているか人気なのかを調査し、自身がどのような方針で活動していくかの判断材料を集めて、分析してください の最新技術動向の研究動向 の最新動向",
      "status": "success",
      "execution_time": 1031.2081829457627,
      "quality_score": 0.3729717943497706,
      "cost": 0.6,
      "themes_found": [
        "技術革新",
        "スケーラビリティ",
        "課題解決"
      ],
      "error": null
    },
    {
      "session_id": "session_20250713_005208_1f3d92",
      "query": "最新のせつなは歌系の活動者です。主な活動として歌を用いたMusicVideoの投稿を考えていますが、それだけだと投稿頻度に難があるとも考えています。\n今後人気や知名度を獲得していくにあたって、既存の歌系インフルエンサー、動画投稿者、VTuberなどがどのようなコンテンツを制作しているか人気なのかを調査し、自身がどのような方針で活動していくかの判断材料を集めて、分析してください の最新研究の実装事例",
      "status": "success",
      "execution_time": 1095.0167414005282,
      "quality_score": 0.43127003420756466,
      "cost": 0.6,
      "themes_found": [
        "スケーラビリティ",
        "市場動向",
        "技術革新"
      ],
      "error": null
    },
    {
      "session_id": "session_20250713_005208_1f3d92",
      "query": "せつなは歌系の活動者です。主な活動として歌を用いたMusicVideoの投稿を考えていますが、それだけだと投稿頻度に難があるとも考えています。\n今後人気や知名度を獲得していくにあたって、既存の歌系インフルエンサー、動画投稿者、VTuberなどがどのようなコンテンツを制作しているか人気なのかを調査し、自身がどのような方針で活動していくかの判断材料を集めて、分析してください の定義と概要の技術分析の研究動向",
      "status": "success",
      "execution_time": 1201.7902673953672,
      "quality_score": 0.3377078944475795,
      "cost": 0.6,
      "themes_found": [
        "将来性",
        "技術革新"
      ],
      "error": null
    },
    {
      "session_id": "session_20250713_005208_069561",
      "query": "せつなは歌系の活動者です。主な活動として歌を用いたMusicVideoの投稿を考えていますが、それだけだと投稿頻度に難があるとも考えています。\n今後人気や知名度を獲得していくにあたって、既存の歌系インフルエンサー、動画投稿者、VTuberなどがどのようなコンテンツを制作しているか人気なのかを調査し、自身がどのような方針で活動していくかの判断材料を集めて、分析してください の全体像の応用可能性",
      "status": "success",
      "execution_time": 1280.238959513162,
      "quality_score": 0.4078523766842545,
      "cost": 0.6,
      "themes_found": [
        "リスク要因"
      ],
      "error": null
    }
  ]
}